template_update_get/__init__.py
template_update_get/tests.py
template_update_get/templatetags/__init__.py
template_update_get/templatetags/template_update_get_tags.py
django_template_update_get-2.0.0.dist-info/LICENSE
django_template_update_get-2.0.0.dist-info/METADATA
django_template_update_get-2.0.0.dist-info/WHEEL
django_template_update_get-2.0.0.dist-info/top_level.txt
django_template_update_get-2.0.0.dist-info/RECORD
