Metadata-Version: 2.1
Name: django-template-update-get
Version: 2.0.0
Summary: Adds an `update_GET` template tag that allows you to substitute parameters into the current request's GET parameters
Home-page: https://github.com/ixc/django-template-update-get
Author: Interaction Consortium
Author-email: studio@interaction.net.au
License: MIT
Requires: django (>=3.0)
Requires-Python: >=3.0
License-File: LICENSE
